ocr/__init__.py
ocr/cli.py
ocr/pdf2text.py
ocr/py.typed
upspawn_ocr_cli-0.1.0b3.dist-info/licenses/LICENSE
upspawn_ocr_cli-0.1.0b3.dist-info/METADATA
upspawn_ocr_cli-0.1.0b3.dist-info/WHEEL
upspawn_ocr_cli-0.1.0b3.dist-info/entry_points.txt
upspawn_ocr_cli-0.1.0b3.dist-info/top_level.txt
upspawn_ocr_cli-0.1.0b3.dist-info/RECORD
