Metadata-Version: 2.4
Name: upspawn-ocr-cli
Version: 0.1.0b3
Summary: Modern, polished CLI to extract text from PDFs using the Mistral OCR API.
Author-email: UpSpawn <opensource@upspawn.com>
License-Expression: MIT
Project-URL: Homepage, https://github.com/upspawn/mistral-ocr-cli
Project-URL: Repository, https://github.com/upspawn/mistral-ocr-cli.git
Project-URL: Issues, https://github.com/upspawn/mistral-ocr-cli/issues
Project-URL: Release Notes, https://github.com/upspawn/mistral-ocr-cli/releases
Keywords: ocr,mistral,pdf,cli,text-extraction
Classifier: Development Status :: 3 - Alpha
Classifier: Environment :: Console
Classifier: Intended Audience :: Developers
Classifier: Intended Audience :: Information Technology
Classifier: Programming Language :: Python
Classifier: Programming Language :: Python :: 3
Classifier: Programming Language :: Python :: 3 :: Only
Classifier: Programming Language :: Python :: 3.9
Classifier: Programming Language :: Python :: 3.10
Classifier: Programming Language :: Python :: 3.11
Classifier: Programming Language :: Python :: 3.12
Classifier: Topic :: Utilities
Requires-Python: >=3.9
License-File: LICENSE
Requires-Dist: mistralai>=1.5.1
Requires-Dist: click>=8.1.0
Requires-Dist: rich>=13.0.0
Requires-Dist: python-dotenv>=1.0.0
Provides-Extra: dev
Requires-Dist: pytest>=7.0.0; extra == "dev"
Requires-Dist: pytest-cov>=4.0.0; extra == "dev"
Requires-Dist: mypy>=1.8.0; extra == "dev"
Requires-Dist: ruff>=0.4.0; extra == "dev"
Requires-Dist: pre-commit>=3.6.0; extra == "dev"
Requires-Dist: black>=24.0.0; extra == "dev"
Dynamic: license-file
